README.txt
setup.py
ansiblator/__init__.py
ansiblator/api.py
ansiblator/version.py
ansiblator.egg-info/PKG-INFO
ansiblator.egg-info/SOURCES.txt
ansiblator.egg-info/dependency_links.txt
ansiblator.egg-info/requires.txt
ansiblator.egg-info/top_level.txt