Metadata-Version: 1.1
Name: ansiblator
Version: 0.5-8-29-09-2014
Summary: Ansiblator - makes Ansible api more pythonic
Home-page: http://www.pripravto.cz
Author: pripravto-service
Author-email: test@dlauhy.cz
License: GPLv3
Keywords: ansible,wrapper,automatization,api
Platform: UNKNOWN
Classifier: Development Status :: 4 - Beta
Classifier: Intended Audience :: Developers
Classifier: Intended Audience :: System Administrators
Classifier: License :: OSI Approved :: GNU General Public License v3 (GPLv3)
Classifier: Operating System :: OS Independent
Classifier: Programming Language :: Python
Classifier: Topic :: Software Development :: Libraries :: Python Modules
